<annotation>
	<folder>add-gaussian</folder>
	<filename>5.jpg</filename>
	<path>D:\add-gaussian\5.jpg</path>
	<source>
		<database>Unknown</database>
	</source>
	<size>
		<width>843</width>
		<height>1024</height>
		<depth>1</depth>
	</size>
	<segmented>0</segmented>
	<object>
		<name>lumbar scoliosis</name>
		<pose>Unspecified</pose>
		<truncated>0</truncated>
		<difficult>0</difficult>
		<bndbox>
			<xmin>353</xmin>
			<ymin>108</ymin>
			<xmax>544</xmax>
			<ymax>600</ymax>
		</bndbox>
	</object>
</annotation>
